NoTorch/KNN.py
NoTorch/__init__.py
notorch-0.1.5.dist-info/licenses/LICENSE
notorch-0.1.5.dist-info/METADATA
notorch-0.1.5.dist-info/WHEEL
notorch-0.1.5.dist-info/top_level.txt
notorch-0.1.5.dist-info/RECORD
